{
  "updatedAt": "2026-06-30T17:11:00.732Z",
  "programs": {
    "btv": [
      {
        "t": "Завинаги с теб",
        "s": 1782815400000,
        "e": 1782819000000
      },
      {
        "t": "Вражда",
        "s": 1782819000000,
        "e": 1782824400000
      },
      {
        "t": "Доброта",
        "s": 1782824400000,
        "e": 1782828000000
      },
      {
        "t": "bTV Новините -",
        "s": 1782828000000,
        "e": 1782829200000
      }
    ],
    "btv-action": [
      {
        "t": "Пряко включване",
        "s": 1782813600000,
        "e": 1782820800000
      },
      {
        "t": "Хуберт без Щалер",
        "s": 1782820800000,
        "e": 1782824400000
      },
      {
        "t": "Изкуството на престъплението",
        "s": 1782824400000,
        "e": 1782828000000
      },
      {
        "t": "Разобличаване",
        "s": 1782828000000,
        "e": 1782831600000
      }
    ],
    "btv-cinema": [
      {
        "t": "Туистърс",
        "s": 1782811800000,
        "e": 1782820800000
      },
      {
        "t": "От местопрестъплението",
        "s": 1782820800000,
        "e": 1782824400000
      },
      {
        "t": "От местопрестъплението",
        "s": 1782824400000,
        "e": 1782828000000
      },
      {
        "t": "Ятаган",
        "s": 1782828000000,
        "e": 1782835200000
      }
    ],
    "btv-comedy": [
      {
        "t": "Двама мъже и половина",
        "s": 1782817200000,
        "e": 1782819000000
      },
      {
        "t": "Двама мъже и половина",
        "s": 1782819000000,
        "e": 1782820800000
      },
      {
        "t": "Новите съседи",
        "s": 1782820800000,
        "e": 1782828000000
      },
      {
        "t": "Татковци",
        "s": 1782828000000,
        "e": 1782831600000
      }
    ],
    "history": [
      {
        "t": "Извънземни от древността , сезон 17 , епизод 5",
        "s": 1782817200000,
        "e": 1782820500000
      },
      {
        "t": "Най-големите загадки в историята , сезон 7 , епизод 9",
        "s": 1782820500000,
        "e": 1782824100000
      },
      {
        "t": "Надпревара за находки , сезон 17 , епизод 5",
        "s": 1782824100000,
        "e": 1782827400000
      },
      {
        "t": "Ловци на складове , сезон 2 , епизод 1",
        "s": 1782827400000,
        "e": 1782828900000
      }
    ],
    "kino-nova": [
      {
        "t": "Бейб в града",
        "s": 1782811500000,
        "e": 1782818700000
      },
      {
        "t": "Туристът – трилър, романтика, екшън /п/. На фона на главозамайващата Венеция, Франк (Джони Деп) се впуска в преследване на романс с Елиза (Анджелина Джоли), но много скоро се оказва, че двамата биват заклещени във водовъртеж от интриги и опасности.",
        "s": 1782818700000,
        "e": 1782826200000
      },
      {
        "t": "Лоши момчета /п/. Героите на Уил Смит и Мартин Лорънс се съюзяват в борбата с престъпността в този криминален екшън за две добри ченгета, които са истински Лоши момчета!",
        "s": 1782826200000,
        "e": 1782835200000
      },
      {
        "t": "От местопрестъплението",
        "s": 1782835200000,
        "e": 1782838800000
      }
    ],
    "max-sport-1": [
      {
        "t": "Финал: Тейлър Фриц",
        "s": 1782817200000,
        "e": 1782822600000
      },
      {
        "t": "Финал: Франсиско Серундоло",
        "s": 1782822600000,
        "e": 1782833400000
      },
      {
        "t": "Финал: Франсиско Серундоло",
        "s": 1782833400000,
        "e": 1782835200000
      },
      {
        "t": "Еврокупа: Бахчешехир Истанбул",
        "s": 1782835200000,
        "e": 1782842400000
      }
    ],
    "max-sport-2": [
      {
        "t": "Women's Amateur Championship: Финал",
        "s": 1782811800000,
        "e": 1782822600000
      },
      {
        "t": "Women's Amateur Championship: Финал",
        "s": 1782822600000,
        "e": 1782824400000
      },
      {
        "t": "DTM 2026: Обзор",
        "s": 1782824400000,
        "e": 1782828000000
      },
      {
        "t": "Carrera Cup'26: Обзор на кръга",
        "s": 1782828000000,
        "e": 1782829800000
      }
    ],
    "max-sport-3": [
      {
        "t": "УЕФА Лига на Конференциите: АЗ Алкмаар",
        "s": 1782817200000,
        "e": 1782824400000
      },
      {
        "t": "Мейджър Лийг Сокър: Синсинати",
        "s": 1782824400000,
        "e": 1782831600000
      },
      {
        "t": "Мейджър Лийг Сокър: Сан Хосе Ърткуейкс",
        "s": 1782831600000,
        "e": 1782838800000
      },
      {
        "t": "Купа на Турция: Генчлербирлиги",
        "s": 1782838800000,
        "e": 1782846000000
      }
    ],
    "max-sport-4": [
      {
        "t": "Ла Лига: Атлетико Мадрид",
        "s": 1782817200000,
        "e": 1782824400000
      },
      {
        "t": "Ла Лига: Реал Сосиедад",
        "s": 1782824400000,
        "e": 1782831600000
      },
      {
        "t": "Ла Лига: Райо Валекано",
        "s": 1782831600000,
        "e": 1782838800000
      },
      {
        "t": "Ла Лига: Жирона",
        "s": 1782838800000,
        "e": 1782846000000
      }
    ],
    "nova-news": [
      {
        "t": "Новините. Обедният информационен блок",
        "s": 1782813600000,
        "e": 1782819600000
      },
      {
        "t": "Твоят ден",
        "s": 1782819600000,
        "e": 1782820800000
      },
      {
        "t": "Новините на NOVA NEWS. Информационна емисия на NOVA NEWS",
        "s": 1782820800000,
        "e": 1782822000000
      },
      {
        "t": "Социална мрежа. Следобеден блок",
        "s": 1782822000000,
        "e": 1782824100000
      }
    ],
    "star-channel": [
      {
        "t": "Семейство Симпсън",
        "s": 1782816900000,
        "e": 1782818700000
      },
      {
        "t": "До смърт",
        "s": 1782818700000,
        "e": 1782822000000
      },
      {
        "t": "Касъл",
        "s": 1782822000000,
        "e": 1782825300000
      },
      {
        "t": "Касъл",
        "s": 1782825300000,
        "e": 1782828600000
      }
    ],
    "star-crime": [
      {
        "t": "Сен Пиер",
        "s": 1782815400000,
        "e": 1782819000000
      },
      {
        "t": "От местопрестъплението: Ню Йорк",
        "s": 1782819000000,
        "e": 1782822600000
      },
      {
        "t": "Дарби и Джоан",
        "s": 1782822600000,
        "e": 1782826200000
      },
      {
        "t": "ВИП: Висок интелектуален потенциал",
        "s": 1782826200000,
        "e": 1782831000000
      }
    ],
    "star-life": [
      {
        "t": "Котешки очи",
        "s": 1782814800000,
        "e": 1782819600000
      },
      {
        "t": "Гувернантката",
        "s": 1782819600000,
        "e": 1782821400000
      },
      {
        "t": "Гувернантката",
        "s": 1782821400000,
        "e": 1782822900000
      },
      {
        "t": "Гувернантката",
        "s": 1782822900000,
        "e": 1782824700000
      }
    ],
    "vivacom-arena": [
      {
        "t": "Закрилникът",
        "s": 1782813600000,
        "e": 1782818700000
      },
      {
        "t": "Око на свидетел",
        "s": 1782818700000,
        "e": 1782824700000
      },
      {
        "t": "Сови и мишки , сезон 15 , епизод 19",
        "s": 1782824700000,
        "e": 1782829500000
      },
      {
        "t": "Свръхестествено",
        "s": 1782829500000,
        "e": 1782834600000
      }
    ],
    "antena-3-internacional": [
      {
        "t": "Espejo Público",
        "s": 1782802560000,
        "e": 1782819060000
      },
      {
        "t": "Cocina Abierta De Karlos Arguiñano",
        "s": 1782819060000,
        "e": 1782820740000
      },
      {
        "t": "El Chiringuito De Jugones",
        "s": 1782820740000,
        "e": 1782824280000
      },
      {
        "t": "A3 Noticias 1",
        "s": 1782824280000,
        "e": 1782826320000
      }
    ],
    "nature-time": [
      {
        "t": "Nomadas del Serengeti",
        "s": 1782817020000,
        "e": 1782820380000
      },
      {
        "t": "Nomadas del Serengeti",
        "s": 1782820380000,
        "e": 1782823680000
      },
      {
        "t": "Crías de las llanuras",
        "s": 1782823680000,
        "e": 1782826980000
      },
      {
        "t": "Valle salvaje",
        "s": 1782826980000,
        "e": 1782830220000
      }
    ],
    "cineedge": [
      {
        "t": "Survivor",
        "s": 1782812640000,
        "e": 1782818880000
      },
      {
        "t": "Check Point",
        "s": 1782818880000,
        "e": 1782824820000
      },
      {
        "t": "Death Squad",
        "s": 1782824820000,
        "e": 1782831060000
      },
      {
        "t": "The Patrol",
        "s": 1782831060000,
        "e": 1782837180000
      }
    ],
    "rock-action": [
      {
        "t": "Rambo: First Blood",
        "s": 1782813000000,
        "e": 1782818400000
      },
      {
        "t": "Death Ring",
        "s": 1782818400000,
        "e": 1782824100000
      },
      {
        "t": "Battleship",
        "s": 1782824100000,
        "e": 1782831600000
      },
      {
        "t": "Vampire Wars: Battle For...",
        "s": 1782831600000,
        "e": 1782837600000
      }
    ],
    "rock-entertainment": [
      {
        "t": "The Wheel Of Time",
        "s": 1782814200000,
        "e": 1782818100000
      },
      {
        "t": "The Wheel Of Time",
        "s": 1782818100000,
        "e": 1782822000000
      },
      {
        "t": "The Wheel Of Time",
        "s": 1782822000000,
        "e": 1782825900000
      },
      {
        "t": "The Wheel Of Time",
        "s": 1782825900000,
        "e": 1782829800000
      }
    ],
    "suprerrix": [
      {
        "t": "Here Kills The Bride",
        "s": 1782814740000,
        "e": 1782819840000
      },
      {
        "t": "73 Questions, Esther Perel",
        "s": 1782819840000,
        "e": 1782820980000
      },
      {
        "t": "73 Questions, Esther Perel",
        "s": 1782820980000,
        "e": 1782822240000
      },
      {
        "t": "Deadly Secrets: The Confession",
        "s": 1782822240000,
        "e": 1782829260000
      }
    ],
    "uniques": [
      {
        "t": "Before We Go",
        "s": 1782816240000,
        "e": 1782821640000
      },
      {
        "t": "Colonials",
        "s": 1782821640000,
        "e": 1782827640000
      },
      {
        "t": "Sinister Tales: The Haunting",
        "s": 1782827640000,
        "e": 1782834720000
      },
      {
        "t": "Lease On Love",
        "s": 1782834720000,
        "e": 1782840180000
      }
    ],
    "discovery-channel": [
      {
        "t": "Come fanno gli animali",
        "s": 1782795000000,
        "e": 1782857100000
      },
      {
        "t": "Come è fatto",
        "s": 1782857100000,
        "e": 1782858900000
      },
      {
        "t": "Come è fatto",
        "s": 1782858900000,
        "e": 1782860700000
      },
      {
        "t": "Come è fatto",
        "s": 1782860700000,
        "e": 1782862500000
      }
    ],
    "dmax": [
      {
        "t": "Border Security: acque di confine",
        "s": 1782811800000,
        "e": 1782818100000
      },
      {
        "t": "Affari al buio",
        "s": 1782818100000,
        "e": 1782821400000
      },
      {
        "t": "Affari a tutti i costi",
        "s": 1782821400000,
        "e": 1782824400000
      },
      {
        "t": "Affari a tutti i costi",
        "s": 1782824400000,
        "e": 1782827700000
      }
    ],
    "food-network": [
      {
        "t": "Panino perfetto on the Road",
        "s": 1782816300000,
        "e": 1782818400000
      },
      {
        "t": "Cucina in balcone con Ruben",
        "s": 1782818400000,
        "e": 1782821100000
      },
      {
        "t": "Cucina in balcone con Ruben",
        "s": 1782821100000,
        "e": 1782824100000
      },
      {
        "t": "Cucina al mare con Ruben",
        "s": 1782824100000,
        "e": 1782826500000
      }
    ],
    "giallo": [
      {
        "t": "L'ispettore Barnaby",
        "s": 1782816600000,
        "e": 1782823800000
      },
      {
        "t": "Shakespeare & Hathaway",
        "s": 1782823800000,
        "e": 1782827400000
      },
      {
        "t": "Shakespeare & Hathaway",
        "s": 1782827400000,
        "e": 1782831000000
      },
      {
        "t": "Miss Fisher: delitti e misteri",
        "s": 1782831000000,
        "e": 1782835200000
      }
    ],
    "nove": [
      {
        "t": "Cash or Trash - Chi offre di piu'?",
        "s": 1782815400000,
        "e": 1782819900000
      },
      {
        "t": "The Cage - Prendi e scappa",
        "s": 1782819900000,
        "e": 1782824100000
      },
      {
        "t": "The Cage - Prendi e scappa",
        "s": 1782824100000,
        "e": 1782828000000
      },
      {
        "t": "Torbidi delitti",
        "s": 1782828000000,
        "e": 1782831300000
      }
    ],
    "real-time": [
      {
        "t": "Cortesie per gli ospiti",
        "s": 1782815100000,
        "e": 1782819000000
      },
      {
        "t": "Casa a prima vista",
        "s": 1782819000000,
        "e": 1782823200000
      },
      {
        "t": "Casa a prima vista",
        "s": 1782823200000,
        "e": 1782827100000
      },
      {
        "t": "Abito da sposa cercasi",
        "s": 1782827100000,
        "e": 1782831000000
      }
    ],
    "turbo": [
      {
        "t": "Vintage Garage",
        "s": 1782814500000,
        "e": 1782818400000
      },
      {
        "t": "Salt Lake Garage",
        "s": 1782818400000,
        "e": 1782822600000
      },
      {
        "t": "Salt Lake Garage",
        "s": 1782822600000,
        "e": 1782826200000
      },
      {
        "t": "Affari a quattro ruote Francia",
        "s": 1782826200000,
        "e": 1782830100000
      }
    ],
    "veronica-disney-jr": [
      {
        "t": "Bluey",
        "s": 1782817440000,
        "e": 1782817860000
      },
      {
        "t": "Bluey",
        "s": 1782817860000,
        "e": 1782818280000
      },
      {
        "t": "Bluey",
        "s": 1782818280000,
        "e": 1782818880000
      },
      {
        "t": "Mickey Mouse Clubhuis+",
        "s": 1782818880000,
        "e": 1782820380000
      }
    ],
    "ziggo-sport": [
      {
        "t": "Wimbledon 2026",
        "s": 1782813600000,
        "e": 1782831600000
      },
      {
        "t": "Wimbledon 2026",
        "s": 1782831600000,
        "e": 1782851400000
      },
      {
        "t": "Ziggo Sport Race Café De Stamtafel",
        "s": 1782851400000,
        "e": 1782855000000
      },
      {
        "t": "Wimbledon Vandaag",
        "s": 1782855000000,
        "e": 1782858600000
      }
    ],
    "mbc-2": [
      {
        "t": "Loving",
        "s": 1782811800000,
        "e": 1782819000000
      },
      {
        "t": "Operation Fortune: Ruse De Guerre",
        "s": 1782819000000,
        "e": 1782826200000
      },
      {
        "t": "Celebrity Scoop",
        "s": 1782826200000,
        "e": 1782828000000
      },
      {
        "t": "Trouble With The Curve",
        "s": 1782828000000,
        "e": 1782834600000
      }
    ],
    "n24-doku": [
      {
        "t": "UFO-Theorien - Zwischen Fakt und Fiktion",
        "s": 1782863100000,
        "e": 1782865800000
      },
      {
        "t": "Spacetime",
        "s": 1782865800000,
        "e": 1782868500000
      },
      {
        "t": "Spacetime",
        "s": 1782868500000,
        "e": 1782871200000
      },
      {
        "t": "Erde an Aliens",
        "s": 1782871200000,
        "e": 1782873900000
      }
    ]
  }
}